stockalert/__init__.py
stockalert/__version__.py
stockalert/async_client.py
stockalert/client.py
stockalert/exceptions.py
stockalert/logging.py
stockalert/py.typed
stockalert/types.py
stockalert/cli/__init__.py
stockalert/cli/main.py
stockalert/resources/__init__.py
stockalert/resources/alerts.py
stockalert/resources/alerts_base.py
stockalert/resources/api_keys.py
stockalert/resources/async_alerts.py
stockalert/resources/async_api_keys.py
stockalert/resources/async_webhooks.py
stockalert/resources/base.py
stockalert/resources/webhooks.py
stockalert-2.0.1.dist-info/METADATA
stockalert-2.0.1.dist-info/WHEEL
stockalert-2.0.1.dist-info/entry_points.txt
stockalert-2.0.1.dist-info/RECORD
