Metadata-Version: 2.4
Name: stockalert
Version: 2.0.1
Summary: Official Python SDK for StockAlert.pro API
Project-URL: Homepage, https://stockalert.pro
Project-URL: Documentation, https://stockalert.pro/api/docs/sdks
Project-URL: Repository, https://github.com/stockalert-pro/python-sdk
Project-URL: Issues, https://github.com/stockalert-pro/python-sdk/issues
Project-URL: Changelog, https://github.com/stockalert-pro/python-sdk/releases
Author-email: "StockAlert.pro" <support@stockalert.pro>
License-Expression: MIT
Keywords: alerts,api,finance,sdk,stockalert,stocks,trading
Classifier: Development Status :: 4 - Beta
Classifier: Intended Audience :: Developers
Classifier: License :: OSI Approved :: MIT License
Classifier: Programming Language :: Python
Classifier: Programming Language :: Python :: 3.8
Classifier: Programming Language :: Python :: 3.9
Classifier: Programming Language :: Python :: 3.10
Classifier: Programming Language :: Python :: 3.11
Classifier: Programming Language :: Python :: 3.12
Classifier: Programming Language :: Python :: Implementation :: CPython
Classifier: Topic :: Office/Business :: Financial
Classifier: Topic :: Software Development :: Libraries :: Python Modules
Requires-Python: >=3.8
Requires-Dist: requests>=2.25.0
Requires-Dist: typing-extensions>=4.0.0; python_version < '3.10'
Provides-Extra: async
Requires-Dist: httpx>=0.24.0; extra == 'async'
Provides-Extra: dev
Requires-Dist: httpx>=0.24.0; extra == 'dev'
Requires-Dist: mypy>=1.0.0; extra == 'dev'
Requires-Dist: pre-commit>=3.0.0; extra == 'dev'
Requires-Dist: pytest-asyncio>=0.21.0; extra == 'dev'
Requires-Dist: pytest-cov>=4.0.0; extra == 'dev'
Requires-Dist: pytest>=7.0.0; extra == 'dev'
Requires-Dist: ruff>=0.1.0; extra == 'dev'
Requires-Dist: types-requests>=2.31.0; extra == 'dev'
